CHANGELOG.md
README.md
nordigen/__init__.py
nordigen/api/__init__.py
nordigen/api/accounts.py
nordigen/api/agreements.py
nordigen/api/institutions.py
nordigen/api/requisitions.py
nordigen/nordigen.py
nordigen/types/__init__.py
nordigen/types/http_enums.py
nordigen/types/types.py
nordigen/utils/__init__.py
nordigen/utils/filter.py
nordigen-1.4.2.dist-info/LICENSE.txt
nordigen-1.4.2.dist-info/WHEEL
nordigen-1.4.2.dist-info/METADATA
nordigen-1.4.2.dist-info/RECORD
