Metadata-Version: 2.1
Name: nordigen
Version: 1.4.2
Summary: Python client for GoCardless Bank Account Data API
Home-page: https://github.com/nordigen/nordigen-python
License: MIT
Keywords: GoCardless,Nordigen,Nordigen API,OpenBanking
Author: Nordigen Solutions
Author-email: bank-account-data-support@gocardless.com
Requires-Python: >=3.8,<4.0
Classifier: License :: OSI Approved :: MIT License
Classifier: Programming Language :: Python :: 3
Classifier: Programming Language :: Python :: 3.10
Classifier: Programming Language :: Python :: 3.8
Classifier: Programming Language :: Python :: 3.9
Requires-Dist: requests (>=2.26.0,<3.0.0)
Project-URL: Repository, https://github.com/nordigen/nordigen-python
